{"metrics": [{"id": "15e89f895b482f9b84ba7274ed18a106", "metric_name": "DriftedColumnsCount(drift_share=0.5)", "config": {"type": "evidently:metric_v2:DriftedColumnsCount", "drift_share": 0.5}, "value": {"count": 2.0, "share": 0.2857142857142857}}, {"id": "130ad6116aba64528983a7733ee109cc", "metric_name": "ValueDrift(column=midprice,method=Wasserstein distance (normed),threshold=0.1)", "config": {"type": "evidently:metric_v2:ValueDrift", "column": "midprice", "method": "Wasserstein distance (normed)", "threshold": 0.1}, "value": 1.963191849284366}, {"id": "d9daa57d3c985ed1fc5c6fd53027f6a2", "metric_name": "ValueDrift(column=midprice_log_return,method=Wasserstein distance (normed),threshold=0.1)", "config": {"type": "evidently:metric_v2:ValueDrift", "column": "midprice_log_return", "method": "Wasserstein distance (normed)", "threshold": 0.1}, "value": 0.0008476418544711034}, {"id": "000d4c46598ed684ea068fdd9ef13bf5", "metric_name": "ValueDrift(column=bid_ask_spread,method=Wasserstein distance (normed),threshold=0.1)", "config": {"type": "evidently:metric_v2:ValueDrift", "column": "bid_ask_spread", "method": "Wasserstein distance (normed)", "threshold": 0.1}, "value": 0.028302967006904274}, {"id": "a621ffd22954caece44aa387f0bc7281", "metric_name": "ValueDrift(column=spread_bps,method=Wasserstein distance (normed),threshold=0.1)", "config": {"type": "evidently:metric_v2:ValueDrift", "column": "spread_bps", "method": "Wasserstein distance (normed)", "threshold": 0.1}, "value": 0.02836497167827611}, {"id": "223fa13a21d1c95d88bb8089302df5a2", "metric_name": "ValueDrift(column=rolling_volatility,method=Wasserstein distance (normed),threshold=0.1)", "config": {"type": "evidently:metric_v2:ValueDrift", "column": "rolling_volatility", "method": "Wasserstein distance (normed)", "threshold": 0.1}, "value": 0.004598347687470716}, {"id": "91ed2b390a4bb8d95769c81adbb40dbb", "metric_name": "ValueDrift(column=trade_intensity,method=Wasserstein distance (normed),threshold=0.1)", "config": {"type": "evidently:metric_v2:ValueDrift", "column": "trade_intensity", "method": "Wasserstein distance (normed)", "threshold": 0.1}, "value": 0.23008183020706421}, {"id": "08f30bf512429e227a448b763ddaa522", "metric_name": "ValueDrift(column=order_book_imbalance,method=Wasserstein distance (normed),threshold=0.1)", "config": {"type": "evidently:metric_v2:ValueDrift", "column": "order_book_imbalance", "method": "Wasserstein distance (normed)", "threshold": 0.1}, "value": 0.051341048109334306}], "tests": []}